openapi_spec_sanitizer/__init__.py
openapi_spec_sanitizer/__main__.py
openapi_spec_sanitizer/analyzer.py
openapi_spec_sanitizer/argparser.py
openapi_spec_sanitizer/dumper.py
openapi_spec_sanitizer/entry.py
openapi_spec_sanitizer/exceptions.py
openapi_spec_sanitizer/loader.py
openapi_spec_sanitizer/sanitizer.py
openapi_spec_sanitizer/stateful.py
openapi_spec_sanitizer-0.1.13.dist-info/LICENSE-2.0.txt
openapi_spec_sanitizer-0.1.13.dist-info/METADATA
openapi_spec_sanitizer-0.1.13.dist-info/WHEEL
openapi_spec_sanitizer-0.1.13.dist-info/top_level.txt
openapi_spec_sanitizer-0.1.13.dist-info/RECORD
