Metadata-Version: 2.1
Name: openapi-spec-sanitizer
Version: 0.1.13
Summary: Sanitizes unused definitions from OpenAPI specification files(YAML and JSON)
Author-email: David Turland <david@turland.org>
License: Apache License Version 2.0
Project-URL: Issues, https://github.com/DavidTurland/openapi-spec-sanitizer/issues
Project-URL: Source, https://github.com/DavidTurland/openapi-spec-sanitizer
Keywords: openapi,sanitize
Classifier: Development Status :: 5 - Production/Stable
Classifier: Intended Audience :: Developers
Classifier: License :: OSI Approved :: Apache Software License
Classifier: Topic :: Software Development :: Libraries :: Python Modules
Classifier: Programming Language :: Python :: 3.8
Classifier: Programming Language :: Python :: 3.9
Classifier: Programming Language :: Python :: 3.10
Requires-Python: >=3
License-File: LICENSE-2.0.txt
Provides-Extra: test
Requires-Dist: pytest (>=7) ; extra == 'test'
Requires-Dist: pytest-cov[all] ; extra == 'test'
Requires-Dist: Flask (<3,>=2) ; extra == 'test'
Requires-Dist: oyaml (>=1.0) ; extra == 'test'
